damascus/__init__.py
damascus/cli.py
damascus/cli_parser.py
damascus/client.py
damascus/exceptions.py
damascus/core/__init__.py
damascus/core/generator.py
damascus/core/schema.py
damascus/core/sdkgen.py
damascus/core/template.py
damascus/core/types.py
damascus-0.1.5.dist-info/licenses/LICENSE
damascus-0.1.5.dist-info/METADATA
damascus-0.1.5.dist-info/WHEEL
damascus-0.1.5.dist-info/entry_points.txt
damascus-0.1.5.dist-info/top_level.txt
damascus-0.1.5.dist-info/RECORD
