Metadata-Version: 2.4
Name: damascus
Version: 0.1.5
Summary: Fast, modern, and open-source OpenAPI SDK Generator
Home-page: https://github.com/beshu-tech/damascus
Author: Beshu Limited
Author-email: info@beshu.tech
License: MIT
Classifier: Programming Language :: Python :: 3
Classifier: License :: OSI Approved :: MIT License
Classifier: Operating System :: OS Independent
Requires-Python: >=3.8
License-File: LICENSE
Requires-Dist: requests
Requires-Dist: pyyaml
Requires-Dist: jinja2
Requires-Dist: certifi
Requires-Dist: charset-normalizer
Requires-Dist: click
Requires-Dist: idna
Requires-Dist: markupsafe
Requires-Dist: packaging
Requires-Dist: typing-extensions
Requires-Dist: urllib3
Provides-Extra: dev
Requires-Dist: black==25.1.0; extra == "dev"
Requires-Dist: coverage==7.8.0; extra == "dev"
Requires-Dist: flake8==7.2.0; extra == "dev"
Requires-Dist: iniconfig==2.1.0; extra == "dev"
Requires-Dist: isort==6.0.1; extra == "dev"
Requires-Dist: mccabe==0.7.0; extra == "dev"
Requires-Dist: mypy==1.15.0; extra == "dev"
Requires-Dist: mypy-extensions==1.0.0; extra == "dev"
Requires-Dist: pathspec==0.12.1; extra == "dev"
Requires-Dist: platformdirs==4.3.7; extra == "dev"
Requires-Dist: pluggy==1.5.0; extra == "dev"
Requires-Dist: pycodestyle==2.13.0; extra == "dev"
Requires-Dist: pyflakes==3.3.2; extra == "dev"
Requires-Dist: pytest==8.3.5; extra == "dev"
Requires-Dist: pytest-cov==6.1.1; extra == "dev"
Requires-Dist: responses==0.25.7; extra == "dev"
Requires-Dist: uv==0.6.14; extra == "dev"
Requires-Dist: types-requests; extra == "dev"
Requires-Dist: types-pyyaml; extra == "dev"
Dynamic: author
Dynamic: author-email
Dynamic: home-page
Dynamic: license-file
Dynamic: requires-python
